elasticache_pyclient/__init__.py
elasticache_pyclient/memcache_client.py
elasticache_pyclient/repeat_timer.py
elasticache_pyclient-2.1.2.dist-info/METADATA
elasticache_pyclient-2.1.2.dist-info/RECORD
elasticache_pyclient-2.1.2.dist-info/WHEEL
elasticache_pyclient-2.1.2.dist-info/top_level.txt
